requestinjector.py
requestinjector-0.9.4.dist-info/LICENSE
requestinjector-0.9.4.dist-info/METADATA
requestinjector-0.9.4.dist-info/WHEEL
requestinjector-0.9.4.dist-info/entry_points.txt
requestinjector-0.9.4.dist-info/top_level.txt
requestinjector-0.9.4.dist-info/RECORD
