Metadata-Version: 2.1
Name: requestinjector
Version: 0.9.4
Summary: scan a URL using one or more given wordlists with optional URL transformations
Home-page: https://github.com/bonifield/RequestInjector
Author: James Bonifield
Author-email: bonifield.tools@gmail.com
License: UNKNOWN
Platform: UNKNOWN
Classifier: Programming Language :: Python :: 3
Classifier: License :: OSI Approved :: MIT License
Classifier: Operating System :: OS Independent
License-File: LICENSE
